_pyicer.cp310-win32.pyd
pyicer/__init__.py
pyicer/_pyicer.pyi
pyicer-0.1.3.dist-info/licenses/LICENSE
pyicer-0.1.3.dist-info/METADATA
pyicer-0.1.3.dist-info/WHEEL
pyicer-0.1.3.dist-info/top_level.txt
pyicer-0.1.3.dist-info/RECORD
