Metadata-Version: 2.4
Name: pyicer
Version: 0.1.3
Summary: Python wrapper for libicer
Home-page: https://github.com/baskiton/pyicer
Author: Alexander Baskikh
Author-email: baskiton@gmail.com
License: MIT
Project-URL: Source, https://github.com/baskiton/pyicer
Project-URL: Bug Tracker, https://github.com/baskiton/pyicer/issues
Classifier: Programming Language :: Python :: 3
Requires-Python: >=3.7
License-File: LICENSE
Requires-Dist: numpy
Dynamic: author
Dynamic: author-email
Dynamic: classifier
Dynamic: description
Dynamic: description-content-type
Dynamic: home-page
Dynamic: license
Dynamic: license-file
Dynamic: project-url
Dynamic: requires-dist
Dynamic: requires-python
Dynamic: summary
